barchart/__init__.py
barchart/uoa.py
barchart/helpers/__init__.py
barchart/helpers/async_request.py
barchart/helpers/errors.py
barchart/helpers/pagination.py
barchart/helpers/parser.py
barchart-0.1.3.dist-info/METADATA
barchart-0.1.3.dist-info/WHEEL
barchart-0.1.3.dist-info/top_level.txt
barchart-0.1.3.dist-info/RECORD
