Metadata-Version: 2.1
Name: barchart
Version: 0.1.3
Summary: The Unofficial API for barchart.com
Home-page: http://github.com/tke578/barchart
Author: Andrew Garcia
Author-email: tke578@gmail.com
License: MIT
Keywords: barchart,api,screener,barchart api,options,unusual options activity
Platform: UNKNOWN
Requires-Dist: requests-html
Requires-Dist: async
Requires-Dist: user-agent
Requires-Dist: pyppeteer
